livecell_tracker/__init__.py
livecell_tracker/annotation/__init__.py
livecell_tracker/annotation/coco_utils.py
livecell_tracker/annotation/fiftyone_app.py
livecell_tracker/annotation/labelme2coco.py
livecell_tracker/core/__init__.py
livecell_tracker/core/datasets.py
livecell_tracker/core/single_cell.py
livecell_tracker/core/utils.py
livecell_tracker/core/visualizer.py
livecell_tracker/preprocess/data_augmentation.py
livecell_tracker/preprocess/utils.py
livecell_tracker/segment/__init__.py
livecell_tracker/segment/detectron_utils.py
livecell_tracker/segment/eval_utils.py
livecell_tracker/segment/segment_utils.py
livecell_tracker/segment/utils.py
livecell_tracker/track/__init__.py
livecell_tracker/track/eval_utils.py
livecell_tracker/track/movie.py
livecell_tracker/track/sort_tracker.py
livecell_tracker/track/sort_tracker_utils.py
livecell_tracker/trajectory/__init__.py
livecell_tracker/trajectory/constants.py
livecell_tracker/trajectory/contour_utils.py
livecell_tracker/trajectory/feature_extractors.py
livecell_tracker/trajectory/contour/__init__.py
livecell_tracker/trajectory/contour/cell_contour.py
livecell_tracker/trajectory/contour/contour_class.py
livecell_tracker/trajectory/legacy_utils/__init__.py
livecell_tracker/trajectory/legacy_utils/batch_apply_cla_traj.py
livecell_tracker/trajectory/legacy_utils/batch_apply_reg_nuc.py
livecell_tracker/trajectory/legacy_utils/batch_apply_reg_traj_with_shadow.py
livecell_tracker/trajectory/legacy_utils/black_border_remove.py
livecell_tracker/trajectory/legacy_utils/cellTool_utils.py
livecell_tracker/trajectory/legacy_utils/cell_class.py
livecell_tracker/trajectory/legacy_utils/cla_seg_model.py
livecell_tracker/trajectory/legacy_utils/cla_seg_model_loss.py
livecell_tracker/trajectory/legacy_utils/cnn_prep_data.py
livecell_tracker/trajectory/legacy_utils/compute_cell_contour.py
livecell_tracker/trajectory/legacy_utils/compute_foreground_background.py
livecell_tracker/trajectory/legacy_utils/config.py
livecell_tracker-0.0.3.dist-info/entry_points.txt
livecell_tracker-0.0.3.dist-info/LICENSE
livecell_tracker-0.0.3.dist-info/WHEEL
livecell_tracker-0.0.3.dist-info/METADATA
livecell_tracker-0.0.3.dist-info/RECORD
